qa_kit/__init__.py
qa_kit/cli.py
qa_kit/generator.py
qa_kit/runner.py
qa_kit/utils.py
qa_kit-0.1.5.dist-info/LICENSE
qa_kit-0.1.5.dist-info/METADATA
qa_kit-0.1.5.dist-info/WHEEL
qa_kit-0.1.5.dist-info/entry_points.txt
qa_kit-0.1.5.dist-info/RECORD
