Metadata-Version: 2.3
Name: qa-kit
Version: 0.1.5
Summary: CLI + generator for REST API pytest integration tests with Allure reporting
License: MIT
Keywords: API testing,pytest,allure,automation,cli,httpx
Author: Roshan Gupta
Author-email: roshanguptamca@gmail.com
Requires-Python: >=3.13,<4.0
Classifier: Development Status :: 4 - Beta
Classifier: Framework :: Pytest
Classifier: Intended Audience :: Developers
Classifier: License :: OSI Approved :: MIT License
Classifier: Programming Language :: Python :: 3
Classifier: Programming Language :: Python :: 3.13
Classifier: Topic :: Software Development :: Testing
Requires-Dist: click (>=8.1.7)
Requires-Dist: httpx (>=0.25.0,<0.26.0)
Requires-Dist: jinja2 (>=3.1.2,<4.0.0)
Requires-Dist: python-dotenv (>=1.0.1,<2.0.0)
Requires-Dist: typer (>=0.12.3)
Project-URL: Homepage, https://github.com/roshanguptamca/qa-kit
Project-URL: Repository, https://github.com/roshanguptamca/qa-kit
